WhatMorse/__init__.py
WhatMorse/whatmorse.py
whatmorse-0.0.1.dist-info/METADATA
whatmorse-0.0.1.dist-info/WHEEL
whatmorse-0.0.1.dist-info/top_level.txt
whatmorse-0.0.1.dist-info/RECORD
